Workbook

Sheet 01 Customer Outcomes
A1: Week 5: Random Variables and Customer Outcomes
A2: Source: Week 5 lecture, slides 3-8. Inputs are entered directly; calculated cells contain formulas.
A4: Input | B4: Value
A5: Purchase probability per customer | B5: 0.4
A7: Code each decision as 1 = purchase, 0 = no purchase. The two customers decide independently.
A9: Customer 1 | B9: Customer 2 | C9: Purchases X | D9: Outcome probability
A10: 0 | B10: 0 | C10: =A10+B10 -> 0 | D10: =IF(A10=1,$B$5,1-$B$5)*IF(B10=1,$B$5,1-$B$5) -> 0.36
A11: 1 | B11: 0 | C11: =A11+B11 -> 1 | D11: =IF(A11=1,$B$5,1-$B$5)*IF(B11=1,$B$5,1-$B$5) -> 0.24
A12: 0 | B12: 1 | C12: =A12+B12 -> 1 | D12: =IF(A12=1,$B$5,1-$B$5)*IF(B12=1,$B$5,1-$B$5) -> 0.24
A13: 1 | B13: 1 | C13: =A13+B13 -> 2 | D13: =IF(A13=1,$B$5,1-$B$5)*IF(B13=1,$B$5,1-$B$5) -> 0.16
A16: Purchases x | B16: f(x)
A17: 0 | B17: =SUMIF($C$10:$C$13,A17,$D$10:$D$13) -> 0.36
A18: 1 | B18: =SUMIF($C$10:$C$13,A18,$D$10:$D$13) -> 0.48
A19: 2 | B19: =SUMIF($C$10:$C$13,A19,$D$10:$D$13) -> 0.16
A20: Total probability | B20: =SUM(B17:B19) -> 1
A22: Four decision outcomes produce only three purchase counts. The probability of one purchase combines two outcomes.
A24: How to recreate this output in Excel
A25: 1. Enter 0.40 in B5. A probability of 40% is entered as 0.40, not 40.
A26: 2. Enter the four 0/1 decision pairs in A10:B13. In C10 enter =A10+B10 and fill down to C13.
A27: 3. In D10 enter =IF(A10=1,$B$5,1-$B$5)*IF(B10=1,$B$5,1-$B$5). Fill down to D13. The $ signs keep B5 fixed.
A28: 4. Enter 0, 1 and 2 in A17:A19. In B17 enter =SUMIF($C$10:$C$13,A17,$D$10:$D$13) and fill down.
A29: 5. In B20 enter =SUM(B17:B19). It must equal 1. Change B5 to see how the distribution changes.

Sheet 02 Daily Sales
A1: Week 5: Daily Sales Distribution and Measures
A2: Source: Week 5 lecture, slides 9-11, 15-16, 20. Inputs are entered directly; calculated cells contain formulas.
A4: Tablets sold x | B4: Days | C4: Probability f(x) | D4: x f(x) | E4: (x - mean)^2 | F4: Weighted square
A5: 0 | B5: 20 | C5: =B5/$B$8 -> 0.2 | D5: =A5*C5 -> 0 | E5: =(A5-$B$11)^2 -> 1.21 | F5: =E5*C5 -> 0.242
A6: 1 | B6: 50 | C6: =B6/$B$8 -> 0.5 | D6: =A6*C6 -> 0.5 | E6: =(A6-$B$11)^2 -> 0.01 | F6: =E6*C6 -> 0.005
A7: 2 | B7: 30 | C7: =B7/$B$8 -> 0.3 | D7: =A7*C7 -> 0.6 | E7: =(A7-$B$11)^2 -> 0.81 | F7: =E7*C7 -> 0.243
A8: Total | B8: =SUM(B5:B7) -> 100 | C8: =SUM(C5:C7) -> 1
A10: Measure | B10: Result
A11: Expected sales | B11: =SUM(D5:D7) -> 1.1
A12: Variance | B12: =SUM(F5:F7) -> 0.49
A13: Standard deviation | B13: =SQRT(B12) -> 0.7
A14: E(X^2) | B14: =SUMPRODUCT(A5:A7,A5:A7,C5:C7) -> 1.7
A15: Variance check | B15: =B14-B11^2 -> 0.49
A17: Event | B17: Probability
A18: Exactly one | B18: =C6 -> 0.5
A19: At most one | B19: =SUM(C5:C6) -> 0.7
A20: At least one | B20: =1-C5 -> 0.8
A21: More than one | B21: =C7 -> 0.3
A22: One to two, inclusive | B22: =SUM(C6:C7) -> 0.8
A24: Expected sales and SD are in tablets; variance is in tablets squared. This is a probability-weighted distribution calculation, not VAR.S.
A41: How to recreate this output in Excel
A42: 1. Enter sales values in A5:A7 and observed day counts in B5:B7. In B8 enter =SUM(B5:B7); keep this total positive.
A43: 2. In C5 enter =B5/$B$8 and fill down. In C8 enter =SUM(C5:C7); the result must be 1.
A44: 3. In D5 enter =A5*C5 and fill down. In B11 enter =SUM(D5:D7) to obtain expected sales.
A45: 4. In E5 enter =(A5-$B$11)^2. In F5 enter =E5*C5. Fill both down. In B12 enter =SUM(F5:F7); in B13 enter =SQRT(B12).
A46: 5. In B14 enter =SUMPRODUCT(A5:A7,A5:A7,C5:C7), then =B14-B11^2 in B15. It must match B12.
A47: 6. Use =C6 for exactly one, =SUM(C5:C6) for at most one, =1-C5 for at least one and =C7 for more than one.
A48: 7. Select A4:A7 and, holding Ctrl, C4:C7. Choose Insert > Column Chart > Clustered Column. Add data labels and use a zero-based probability axis.

Sheet 03 Uniform Vouchers
A1: Week 5: Discrete Uniform Distribution
A2: Source: Week 5 lecture, slides 12. Inputs are entered directly; calculated cells contain formulas.
A4: Voucher value (MAD) | B4: Probability
A5: 10 | B5: =1/COUNT($A$5:$A$8) -> 0.25
A6: 20 | B6: =1/COUNT($A$5:$A$8) -> 0.25
A7: 30 | B7: =1/COUNT($A$5:$A$8) -> 0.25
A8: 40 | B8: =1/COUNT($A$5:$A$8) -> 0.25
A10: Total probability | B10: =SUM(B5:B8) -> 1
A12: Minimum voucher value | B12: 30
A13: P(value >= minimum) | B13: =SUMIF(A5:A8,">="&B12,B5:B8) -> 0.5
A15: Each of the four vouchers is equally likely. Merely listing four values does not establish this assumption.
A17: How to recreate this output in Excel
A18: 1. Enter the four voucher values in A5:A8.
A19: 2. In B5 enter =1/COUNT($A$5:$A$8) and fill down to B8. This formula uses the stated equal-probability assumption.
A20: 3. In B10 enter =SUM(B5:B8) and check that it equals 1.
A21: 4. Enter the minimum value in B12. In B13 enter =SUMIF(A5:A8,">="&B12,B5:B8). Change B12 to calculate another threshold probability.

Sheet 04 Variability
A1: Week 5: Same Mean, Different Variability
A2: Source: Week 5 lecture, slides 17. Inputs are entered directly; calculated cells contain formulas.
A4: Tablets sold x | B4: Distribution A | C4: Distribution B | D4: A weighted square | E4: B weighted square
A5: 0 | B5: ='02 Daily Sales'!C5 -> 0.2 | C5: 0.4 | D5: =(A5-$B$11)^2*B5 -> 0.242 | E5: =(A5-$C$11)^2*C5 -> 0.484
A6: 1 | B6: ='02 Daily Sales'!C6 -> 0.5 | C6: 0.1 | D6: =(A6-$B$11)^2*B6 -> 0.005 | E6: =(A6-$C$11)^2*C6 -> 0.001
A7: 2 | B7: ='02 Daily Sales'!C7 -> 0.3 | C7: 0.5 | D7: =(A7-$B$11)^2*B7 -> 0.243 | E7: =(A7-$C$11)^2*C7 -> 0.405
A9: Measure | B9: Distribution A | C9: Distribution B
A10: Probability sum | B10: =SUM(B5:B7) -> 1 | C10: =SUM(C5:C7) -> 1
A11: Expected value | B11: =SUMPRODUCT(A5:A7,B5:B7) -> 1.1 | C11: =SUMPRODUCT(A5:A7,C5:C7) -> 1.1
A12: Variance | B12: =SUM(D5:D7) -> 0.49 | C12: =SUM(E5:E7) -> 0.89
A13: Standard deviation | B13: =SQRT(B12) -> 0.7 | C13: =SQRT(C12) -> 0.94339811
A14: Probability check | B14: =IF(AND(ABS(B10-1)<0.000000001,MIN(B5:B7)>=0),"OK","Check probabilities") -> OK | C14: =IF(AND(ABS(C10-1)<0.000000001,MIN(C5:C7)>=0),"OK","Check probabilities") -> OK
A16: Both means are 1.10. B puts more probability on 0 and 2, producing the larger variance. Keep probabilities nonnegative and summing to 1.
A33: How to recreate this output in Excel
A34: 1. Use the sales values in A5:A7. Distribution A links to the earlier sales sheet. Enter B probabilities 0.40, 0.10 and 0.50 in C5:C7.
A35: 2. Calculate each probability sum with SUM. For the means, use =SUMPRODUCT(A5:A7,B5:B7) and =SUMPRODUCT(A5:A7,C5:C7).
A36: 3. In D5 enter =(A5-$B$11)^2*B5. In E5 enter =(A5-$C$11)^2*C5. Fill down to row 7.
A37: 4. Sum D5:D7 and E5:E7 to obtain the variances. Apply SQRT to obtain each SD.
A38: 5. Select A4:C7, then Insert > Column Chart > Clustered Column. Keep the probability axis starting at zero.
A39: 6. Change C5:C7 while retaining a total of 1. Compare both the mean and SD, rather than only the tallest bar.

Sheet 05 Sales and Profit
A1: Week 5: From Sales to Profit
A2: Source: Week 5 lecture, slides 21-22. Inputs are entered directly; calculated cells contain formulas.
A4: Input | B4: MAD
A5: Net amount per tablet | B5: 80
A6: Fixed daily operating cost | B6: 120
A9: Tablets sold x | B9: Probability | C9: Profit Y | D9: Y f(x) | E9: Y - mean | F9: Weighted square
A10: ='02 Daily Sales'!A5 -> 0 | B10: ='02 Daily Sales'!C5 -> 0.2 | C10: =$B$5*A10-$B$6 -> -120 | D10: =C10*B10 -> -24 | E10: =C10-$B$15 -> -88 | F10: =E10^2*B10 -> 1548.8
A11: ='02 Daily Sales'!A6 -> 1 | B11: ='02 Daily Sales'!C6 -> 0.5 | C11: =$B$5*A11-$B$6 -> -40 | D11: =C11*B11 -> -20 | E11: =C11-$B$15 -> -8 | F11: =E11^2*B11 -> 32
A12: ='02 Daily Sales'!A7 -> 2 | B12: ='02 Daily Sales'!C7 -> 0.3 | C12: =$B$5*A12-$B$6 -> 40 | D12: =C12*B12 -> 12 | E12: =C12-$B$15 -> 72 | F12: =E12^2*B12 -> 1555.2
A14: Measure | B14: Result
A15: Expected profit (MAD) | B15: =SUM(D10:D12) -> -32
A16: Variance (MAD squared) | B16: =SUM(F10:F12) -> 3136
A17: SD (MAD) | B17: =SQRT(B16) -> 56
A18: Probability of a loss | B18: =SUMIF(C10:C12,"<0",B10:B12) -> 0.7
A20: Mean: transformation check | B20: =B5*'02 Daily Sales'!B11-B6 -> -32
A21: Variance: transformation check | B21: =B5^2*'02 Daily Sales'!B12 -> 3136
A22: SD: transformation check | B22: =ABS(B5)*'02 Daily Sales'!B13 -> 56
A24: Y = aX - cost. Fixed cost changes expected profit, not its variance. The coefficient a scales SD by ABS(a) and variance by a squared.
A26: How to recreate this output in Excel
A27: 1. Enter 80 in B5 and 120 in B6. Link A10:B12 to the sales values and probabilities on 02 Daily Sales.
A28: 2. In C10 enter =$B$5*A10-$B$6. In D10 enter =C10*B10. Fill both formulas down through row 12.
A29: 3. In B15 enter =SUM(D10:D12). In E10 enter =C10-$B$15 and in F10 enter =E10^2*B10. Fill down.
A30: 4. Enter =SUM(F10:F12) in B16 and =SQRT(B16) in B17. In B18 use =SUMIF(C10:C12,"<0",B10:B12).
A31: 5. Check the mean using coefficient times E(X) minus fixed cost. Check variance with coefficient squared times Var(X), not VAR.S on three profit values.
A32: 6. Change only B6: expected profit changes while variance and SD remain unchanged. Change B5 to see the scaling effect.

Sheet 06 Joint Distribution
A1: Week 5: Joint and Marginal Distributions
A2: Source: Week 5 lecture, slides 25-28. Inputs are entered directly; calculated cells contain formulas.
A4: North sales x | B4: South y=0: days | C4: South y=1: days | D4: Total days
A5: 0 | B5: 15 | C5: 5 | D5: =SUM(B5:C5) -> 20
A6: 1 | B6: 20 | C6: 30 | D6: =SUM(B6:C6) -> 50
A7: 2 | B7: 5 | C7: 25 | D7: =SUM(B7:C7) -> 30
A8: Total days | B8: =SUM(B5:B7) -> 40 | C8: =SUM(C5:C7) -> 60 | D8: =SUM(D5:D7) -> 100
A11: North sales x | B11: South y=0 | C11: South y=1 | D11: North marginal
A12: =A5 -> 0 | B12: =B5/$D$8 -> 0.15 | C12: =C5/$D$8 -> 0.05 | D12: =SUM(B12:C12) -> 0.2
A13: =A6 -> 1 | B13: =B6/$D$8 -> 0.2 | C13: =C6/$D$8 -> 0.3 | D13: =SUM(B13:C13) -> 0.5
A14: =A7 -> 2 | B14: =B7/$D$8 -> 0.05 | C14: =C7/$D$8 -> 0.25 | D14: =SUM(B14:C14) -> 0.3
A15: South marginal | B15: =SUM(B12:B14) -> 0.4 | C15: =SUM(C12:C14) -> 0.6 | D15: =SUM(D12:D14) -> 1
A18: Quantity | B18: Result
A19: P(Y=1 | X=2) | B19: =C14/D14 -> 0.83333333
A20: P(Y=1) | B20: =C15 -> 0.6
A21: P(X=2, Y=1) | B21: =C14 -> 0.25
A22: P(X=2) times P(Y=1) | B22: =D14*C15 -> 0.18
A24: North mean | B24: =SUMPRODUCT(A12:A14,D12:D14) -> 1.1
A25: North variance | B25: =SUMPRODUCT(A12:A14,A12:A14,D12:D14)-B24^2 -> 0.49
A26: South mean | B26: =0*B15+1*C15 -> 0.6
A27: South variance | B27: =0^2*B15+1^2*C15-B26^2 -> 0.24
A29: The joint probability and product of marginals differ, so the variables are not independent. Keep total days and the conditioning row total positive.
A31: How to recreate this output in Excel
A32: 1. Enter the six observed counts in B5:C7. Sum each row in D5:D7 and each column in row 8.
A33: 2. In B12 enter =B5/$D$8. Fill across to C12, then down to row 14. The denominator is the total number of days.
A34: 3. Sum across each joint-probability row for the North marginal in D12:D14. Sum each column in row 15 for the South marginal.
A35: 4. Use =C14/D14 for P(Y=1 given X=2). Compare it with =C15, the unconditional probability.
A36: 5. Compare =C14 with =D14*C15. One unequal pair is sufficient to rule out independence.
A37: 6. Use SUMPRODUCT of the North values and their marginal probabilities for its mean. For variance, use E(X^2)-E(X)^2; use the South probabilities for its measures.

Sheet 07 Total Sales
A1: Week 5: Distribution of Total Sales
A2: Source: Week 5 lecture, slides 29-30, 32. Inputs are entered directly; calculated cells contain formulas.
A4: Total s = X + Y | B4: P(S=s) | C4: s P(S=s) | D4: s - mean | E4: Weighted square
A5: 0 | B5: ='06 Joint Distribution'!B12 -> 0.15 | C5: =A5*B5 -> 0 | D5: =A5-$B$12 -> -1.7 | E5: =D5^2*B5 -> 0.4335
A6: 1 | B6: ='06 Joint Distribution'!C12+'06 Joint Distribution'!B13 -> 0.25 | C6: =A6*B6 -> 0.25 | D6: =A6-$B$12 -> -0.7 | E6: =D6^2*B6 -> 0.1225
A7: 2 | B7: ='06 Joint Distribution'!C13+'06 Joint Distribution'!B14 -> 0.35 | C7: =A7*B7 -> 0.7 | D7: =A7-$B$12 -> 0.3 | E7: =D7^2*B7 -> 0.0315
A8: 3 | B8: ='06 Joint Distribution'!C14 -> 0.25 | C8: =A8*B8 -> 0.75 | D8: =A8-$B$12 -> 1.3 | E8: =D8^2*B8 -> 0.4225
A9: Total probability | B9: =SUM(B5:B8) -> 1
A11: Measure | B11: Result
A12: Expected total sales | B12: =SUM(C5:C8) -> 1.7
A13: Variance | B13: =SUM(E5:E8) -> 1.01
A14: Standard deviation | B14: =SQRT(B13) -> 1.0049876
A16: Sum of outlet means | B16: ='06 Joint Distribution'!B24+'06 Joint Distribution'!B26 -> 1.7
A17: Sum of outlet variances | B17: ='06 Joint Distribution'!B25+'06 Joint Distribution'!B27 -> 0.73
A18: Difference in variances | B18: =B13-B17 -> 0.28
A19: Covariance from identity | B19: =B18/2 -> 0.14
A21: For S=1, combine (0,1) and (1,0); for S=2, combine (1,1) and (2,0). Means add without independence. Variances also require twice the covariance.
A23: How to recreate this output in Excel
A24: 1. Enter totals 0, 1, 2 and 3 in A5:A8. For each total, add the appropriate cells from the joint probability table on 06 Joint Distribution.
A25: 2. In C5 enter =A5*B5 and fill down. In B12 enter =SUM(C5:C8).
A26: 3. In D5 enter =A5-$B$12. In E5 enter =D5^2*B5. Fill down to row 8.
A27: 4. In B13 enter =SUM(E5:E8); in B14 enter =SQRT(B13).
A28: 5. Link B16 to the sum of the marginal means and B17 to the sum of the marginal variances on 06 Joint Distribution.
A29: 6. In B18 enter =B13-B17; in B19 enter =B18/2. The result is the covariance, checked directly on the next sheet.

Sheet 08 Covariance
A1: Week 5: Covariance and Correlation
A2: Source: Week 5 lecture, slides 31-33. Inputs are entered directly; calculated cells contain formulas.
A4: x | B4: y | C4: Joint probability | D4: x - mean X | E4: y - mean Y | F4: Weighted product
A5: 0 | B5: 0 | C5: ='06 Joint Distribution'!B12 -> 0.15 | D5: =A5-$B$14 -> -1.1 | E5: =B5-$B$15 -> -0.6 | F5: =D5*E5*C5 -> 0.099
A6: 0 | B6: 1 | C6: ='06 Joint Distribution'!C12 -> 0.05 | D6: =A6-$B$14 -> -1.1 | E6: =B6-$B$15 -> 0.4 | F6: =D6*E6*C6 -> -0.022
A7: 1 | B7: 0 | C7: ='06 Joint Distribution'!B13 -> 0.2 | D7: =A7-$B$14 -> -0.1 | E7: =B7-$B$15 -> -0.6 | F7: =D7*E7*C7 -> 0.012
A8: 1 | B8: 1 | C8: ='06 Joint Distribution'!C13 -> 0.3 | D8: =A8-$B$14 -> -0.1 | E8: =B8-$B$15 -> 0.4 | F8: =D8*E8*C8 -> -0.012
A9: 2 | B9: 0 | C9: ='06 Joint Distribution'!B14 -> 0.05 | D9: =A9-$B$14 -> 0.9 | E9: =B9-$B$15 -> -0.6 | F9: =D9*E9*C9 -> -0.027
A10: 2 | B10: 1 | C10: ='06 Joint Distribution'!C14 -> 0.25 | D10: =A10-$B$14 -> 0.9 | E10: =B10-$B$15 -> 0.4 | F10: =D10*E10*C10 -> 0.09
A13: Measure | B13: Result
A14: Mean X | B14: ='06 Joint Distribution'!B24 -> 1.1
A15: Mean Y | B15: ='06 Joint Distribution'!B26 -> 0.6
A16: Covariance | B16: =SUM(F5:F10) -> 0.14
A17: SD X | B17: =SQRT('06 Joint Distribution'!B25) -> 0.7
A18: SD Y | B18: =SQRT('06 Joint Distribution'!B27) -> 0.48989795
A19: Correlation | B19: =B16/(B17*B18) -> 0.40824829
A20: Covariance identity check | B20: ='07 Total Sales'!B19 -> 0.14
A22: Do not use CORREL on the six outcome rows: their probabilities differ. Weight the deviations, then divide covariance by the two distribution SDs.
A24: How to recreate this output in Excel
A25: 1. List all six (x,y) pairs in A5:B10. Link C5:C10 to their joint probabilities on 06 Joint Distribution.
A26: 2. Link B14 and B15 to the marginal means. In D5 enter =A5-$B$14 and in E5 enter =B5-$B$15. Fill down.
A27: 3. In F5 enter =D5*E5*C5 and fill down to F10. Enter =SUM(F5:F10) in B16.
A28: 4. Calculate the two marginal SDs in B17:B18 by applying SQRT to the marginal variances.
A29: 5. In B19 enter =B16/(B17*B18). Correlation has no units. B20 links to the independent variance-of-a-sum check.

Sheet 09 Fund Returns
A1: Week 5: Fund Returns, Variances and Covariance
A2: Source: Week 5 lecture, slides 37-39. Inputs are entered directly; calculated cells contain formulas.
A4: Economic state | B4: Probability | C4: Alpha return (%) | D4: Beta return (%)
A5: Weak | B5: 0.25 | C5: -4 | D5: 12
A6: Moderate | B6: 0.5 | C6: 8 | D6: 6
A7: Strong | B7: 0.25 | C7: 20 | D7: 4
A8: Probability sum | B8: =SUM(B5:B7) -> 1
A10: Measure | B10: Alpha | C10: Beta
A11: Expected return (%) | B11: =SUMPRODUCT(B5:B7,C5:C7) -> 8 | C11: =SUMPRODUCT(B5:B7,D5:D7) -> 7
A12: Variance (pp squared) | B12: =SUM(E18:E20) -> 72 | C12: =SUM(F18:F20) -> 9
A13: SD (percentage points) | B13: =SQRT(B12) -> 8.4852814 | C13: =SQRT(C12) -> 3
A17: State | B17: Probability | C17: Alpha deviation | D17: Beta deviation | E17: Alpha weighted square | F17: Beta weighted square | G17: Weighted product
A18: =A5 -> Weak | B18: =B5 -> 0.25 | C18: =C5-$B$11 -> -12 | D18: =D5-$C$11 -> 5 | E18: =C18^2*B18 -> 36 | F18: =D18^2*B18 -> 6.25 | G18: =C18*D18*B18 -> -15
A19: =A6 -> Moderate | B19: =B6 -> 0.5 | C19: =C6-$B$11 -> 0 | D19: =D6-$C$11 -> -1 | E19: =C19^2*B19 -> 0 | F19: =D19^2*B19 -> 0.5 | G19: =C19*D19*B19 -> 0
A20: =A7 -> Strong | B20: =B7 -> 0.25 | C20: =C7-$B$11 -> 12 | D20: =D7-$C$11 -> -3 | E20: =C20^2*B20 -> 36 | F20: =D20^2*B20 -> 2.25 | G20: =C20*D20*B20 -> -9
A23: Covariance (pp squared) | B23: =SUM(G18:G20) -> -24
A24: Correlation | B24: =B23/(B13*C13) -> -0.94280904
A25: Probability check | B25: =IF(AND(ABS(B8-1)<0.000000001,MIN(B5:B7)>=0),"OK","Check probabilities") -> OK
A27: Enter return 8% as the number 8, not as 8%. Probabilities use decimals. SD is in percentage points (pp); variance and covariance use pp squared.
A29: How to recreate this output in Excel
A30: 1. Enter state probabilities in B5:B7 and returns in C5:D7. Use 8 for an 8% return; do not apply Excel percentage formatting to returns.
A31: 2. In B11 enter =SUMPRODUCT(B5:B7,C5:C7); in C11 use =SUMPRODUCT(B5:B7,D5:D7).
A32: 3. Link the states and probabilities to A18:B20. In C18 enter =C5-$B$11; in D18 enter =D5-$C$11. Fill down.
A33: 4. In E18 enter =C18^2*B18; in F18 enter =D18^2*B18; in G18 enter =C18*D18*B18. Fill all three down.
A34: 5. Sum E18:E20 and F18:F20 for the variances. Use SQRT for SDs. Sum G18:G20 for covariance.
A35: 6. In B24 enter =B23/(B13*C13). Keep probabilities summing to 1 when editing the inputs.

Sheet 10 Portfolio
A1: Week 5: A Two-Fund Portfolio
A2: Source: Week 5 lecture, slides 40-41. Inputs are entered directly; calculated cells contain formulas.
A4: Allocation | B4: Weight
A5: Alpha weight | B5: 0.5
A6: Beta weight | B6: =1-B5 -> 0.5
A9: Economic state | B9: Probability | C9: Alpha return (%) | D9: Beta return (%) | E9: Portfolio return (%) | F9: Weighted square
A10: ='09 Fund Returns'!A5 -> Weak | B10: ='09 Fund Returns'!B5 -> 0.25 | C10: ='09 Fund Returns'!C5 -> -4 | D10: ='09 Fund Returns'!D5 -> 12 | E10: =$B$5*C10+$B$6*D10 -> 4 | F10: =(E10-$B$16)^2*B10 -> 3.0625
A11: ='09 Fund Returns'!A6 -> Moderate | B11: ='09 Fund Returns'!B6 -> 0.5 | C11: ='09 Fund Returns'!C6 -> 8 | D11: ='09 Fund Returns'!D6 -> 6 | E11: =$B$5*C11+$B$6*D11 -> 7 | F11: =(E11-$B$16)^2*B11 -> 0.125
A12: ='09 Fund Returns'!A7 -> Strong | B12: ='09 Fund Returns'!B7 -> 0.25 | C12: ='09 Fund Returns'!C7 -> 20 | D12: ='09 Fund Returns'!D7 -> 4 | E12: =$B$5*C12+$B$6*D12 -> 12 | F12: =(E12-$B$16)^2*B12 -> 5.0625
A15: Measure | B15: Result
A16: Expected return (%) | B16: =SUMPRODUCT(B10:B12,E10:E12) -> 7.5
A17: Variance (pp squared) | B17: =SUM(F10:F12) -> 8.25
A18: SD (percentage points) | B18: =SQRT(B17) -> 2.8722813
A20: Mean formula check | B20: =B5*'09 Fund Returns'!B11+B6*'09 Fund Returns'!C11 -> 7.5
A21: Alpha variance term | B21: =B5^2*'09 Fund Returns'!B12 -> 18
A22: Beta variance term | B22: =B6^2*'09 Fund Returns'!C12 -> 2.25
A23: Covariance term | B23: =2*B5*B6*'09 Fund Returns'!B23 -> -12
A24: Variance formula check | B24: =SUM(B21:B23) -> 8.25
A25: Difference: direct vs formula | B25: =B17-B24 -> 0
A26: Weighted SD: not portfolio SD | B26: =B5*'09 Fund Returns'!B13+B6*'09 Fund Returns'!C13 -> 5.7426407
A28: The state-by-state and portfolio-formula calculations agree. Portfolio SD is not the weighted average of individual SDs. These are hypothetical scenarios, not guaranteed returns.
A30: How to recreate this output in Excel
A31: 1. Enter the Alpha weight in B5 as 50% or 0.50. In B6 enter =1-B5. Keep B5 between 0 and 1.
A32: 2. Link A10:D12 to the three state rows on 09 Fund Returns.
A33: 3. In E10 enter =$B$5*C10+$B$6*D10 and fill down. In B16 enter =SUMPRODUCT(B10:B12,E10:E12).
A34: 4. In F10 enter =(E10-$B$16)^2*B10 and fill down. Sum F10:F12 in B17 and use =SQRT(B17) in B18.
A35: 5. For the variance check, multiply each fund variance by its weight squared. Add twice the product of the weights and the covariance, as shown in B21:B24.
A36: 6. B25 must be zero apart from rounding. Change B5 and compare return and SD; do not use the weighted SD in B26 as portfolio risk.
